atomrdf/__init__.py
atomrdf/encoder.py
atomrdf/graph.py
atomrdf/io.py
atomrdf/json_io.py
atomrdf/mp.py
atomrdf/namespace.py
atomrdf/properties.py
atomrdf/sample.py
atomrdf/stores.py
atomrdf/structure.py
atomrdf/visualize.py
atomrdf/data/asmo.owl
atomrdf/data/cmso.owl
atomrdf/data/dft_template.yml
atomrdf/data/element.yml
atomrdf/data/ldo.owl
atomrdf/data/md_template.yml
atomrdf/data/pldo.owl
atomrdf/data/podo.owl
atomrdf/network/__init__.py
atomrdf/network/network.py
atomrdf/network/ontology.py
atomrdf/network/parser.py
atomrdf/network/patch.py
atomrdf/network/term.py
atomrdf/workflow/__init__.py
atomrdf/workflow/workflow.py
atomrdf/workflow/pyiron/__init__.py
atomrdf/workflow/pyiron/calphy.py
atomrdf/workflow/pyiron/lammps.py
atomrdf/workflow/pyiron/murnaghan.py
atomrdf/workflow/pyiron/pyiron.py
atomrdf/workflow/pyiron/quasiharmonic.py
atomrdf/workflow/pyiron/vasp.py
atomrdf/workflow/qe/__init__.py
atomrdf/workflow/qe/qe.py
atomrdf-0.9.17.dist-info/LICENSE
atomrdf-0.9.17.dist-info/METADATA
atomrdf-0.9.17.dist-info/WHEEL
atomrdf-0.9.17.dist-info/top_level.txt
atomrdf-0.9.17.dist-info/RECORD
